{
	"games": [
		{
			"id": "backgammon",
			"title": "Backgammon - Fair Board Games",
			"subtitle": "Classic strategy board game",
			"description": "100% FAIR DICE · PURE STRATEGY\n\nWelcome to Backgammon - Fair Board Games — the classic board strategy where every roll is provably fair and a match starts in seconds!\n\nFEATURES:\n• Provably Fair RNG – open-source code & in-app seeds for self-verification\n• Quick Matchmaking – tap Play and join a ranked game instantly\n• Smart Bot Backup – no waiting; bots use the same fair dice and affect your rank\n• Friend Links – share a URL via WhatsApp, iMessage or Facebook for 1-on-1 duels\n• Pet Companion – feed, level up and earn bonus coins daily\n\nVERIFY EVERY ROLL:\n• Both seeds shown after each game—run the script and confirm the outcome\n• Bots follow identical rules, keeping competition honest\n\nPLAY YOUR WAY:\n• Ranked ladder, casual duels or AI practice\n• Watch live games or replay every move\n• Progress and pets sync across all devices\n\nDownload now and make every roll count!",
			"icon": "https://dl.zeroplay.cc/metadata/backgammon/icon.png",
			"banner": "https://dl.zeroplay.cc/metadata/backgammon/banner.png",
			"videoUrl": "https://dl.zeroplay.cc/metadata/backgammon/preview%400.5x.mp4",
			"posterUrl": "https://dl.zeroplay.cc/metadata/backgammon/poster.jpg",
			"screenshots": [
				"https://dl.zeroplay.cc/metadata/backgammon/screenshot-01.jpg",
				"https://dl.zeroplay.cc/metadata/backgammon/screenshot-02.jpg",
				"https://dl.zeroplay.cc/metadata/backgammon/screenshot-03.jpg",
				"https://dl.zeroplay.cc/metadata/backgammon/screenshot-04.jpg",
				"https://dl.zeroplay.cc/metadata/backgammon/screenshot-05.jpg",
				"https://dl.zeroplay.cc/metadata/backgammon/screenshot-06.jpg"
			],
			"orientation": "landscape",
			"stores": {
				"appStore": "https://apps.apple.com/app/id6739750400",
				"googlePlay": "https://play.google.com/store/apps/details?id=io.zeroplay.backgammon2",
				"h5": "https://play.zeroplay.io/backgammon"
			},
			"socialMedia": {
				"enabled": false,
				"facebook": "https://facebook.com/backgammongo",
				"instagram": "https://instagram.com/backgammongo",
				"twitter": "https://twitter.com/backgammongo"
			}
		},
		{
			"id": "solitaire",
			"title": "Solitaire - Classic Card Game",
			"subtitle": "Timeless patience game",
			"description": "Experience the classic Klondike Solitaire with smooth animations and beautiful design. Perfect for all devices, enjoy the timeless card game loved by millions worldwide.\n\nMaster your skills with intelligent hint system that suggests the best moves, unlimited undo to correct mistakes, and auto-complete feature to finish games quickly. Track your progress with real-time statistics including score, time, and move count. Auto-save ensures you never lose progress.\n\nCompete on global leaderboards, regional rankings, and challenge friends. Choose your competition style: highest score, fastest time, or fewest moves. Complete daily challenges to earn coins and unlock beautiful background skins to personalize your game. Enjoy automatic dark and light theme switching with haptic feedback for every interaction.\n\nPerfect for commuting, breaks, or relaxing before bed. Play offline anytime, anywhere. Download now and start your Solitaire journey.",
			"icon": "https://dl.zeroplay.cc/metadata/solitaire/icon.png",
			"banner": "https://dl.zeroplay.cc/metadata/solitaire/banner.png",
			"videoUrl": "https://dl.zeroplay.cc/metadata/solitaire/preview%400.5x.mp4",
			"posterUrl": "https://dl.zeroplay.cc/metadata/solitaire/poster.jpg",
			"screenshots": [
				"https://dl.zeroplay.cc/metadata/solitaire/screenshot-01.jpg",
				"https://dl.zeroplay.cc/metadata/solitaire/screenshot-02.jpg",
				"https://dl.zeroplay.cc/metadata/solitaire/screenshot-03.jpg",
				"https://dl.zeroplay.cc/metadata/solitaire/screenshot-04.jpg",
				"https://dl.zeroplay.cc/metadata/solitaire/screenshot-05.jpg"
			],
			"orientation": "portrait",
			"stores": {
				"appStore": "https://apps.apple.com/app/id6753621971",
				"googlePlay": "https://play.google.com/store/apps/details?id=io.zeroplay.solitaire",
				"h5": "https://play.zeroplay.io/solitaire"
			},
			"socialMedia": {
				"enabled": false
			}
		}
	]
}
